streamlit_kickoff_cli/__init__.py
streamlit_kickoff_cli/custom_logging.py
streamlit_kickoff_cli/entrypoint.py
streamlit_kickoff_cli/dev/__init__.py
streamlit_kickoff_cli/dev/command.py
streamlit_kickoff_cli/kick/__init__.py
streamlit_kickoff_cli/kick/command.py
streamlit_kickoff_cli/kill/__init__.py
streamlit_kickoff_cli/kill/command.py
streamlit_kickoff_cli/list/__init__.py
streamlit_kickoff_cli/list/command.py
streamlit_kickoff_cli/new/__init__.py
streamlit_kickoff_cli/new/command.py
streamlit_kickoff_cli-0.1.1.dist-info/LICENSE
streamlit_kickoff_cli-0.1.1.dist-info/METADATA
streamlit_kickoff_cli-0.1.1.dist-info/WHEEL
streamlit_kickoff_cli-0.1.1.dist-info/entry_points.txt
streamlit_kickoff_cli-0.1.1.dist-info/top_level.txt
streamlit_kickoff_cli-0.1.1.dist-info/RECORD
