Metadata-Version: 2.1
Name: streamlit-kickoff-cli
Version: 0.1.1
Summary: stk is a simple CLI to kickoff and manage Streamlit projects
Author-email: Arnaud Miribel <arnaudmiribel@gmail.com>
License: Copyright (c) 2021 - Arnaud Miribel arnaudmiribel@gmail.com        
Project-URL: Homepage, https://github.com/arnaudmiribel/streamlit-kickoff-cli
Project-URL: Bug Tracker, https://github.com/arnaudmiribel/streamlit-kickoff-cli/issues
Keywords: python,streamlit,cli
Classifier: Programming Language :: Python :: 3
Requires-Python: >=3.6
License-File: LICENSE
